install/InstallServer_s1.ini
install/__init__.py
install/installserver.py
rteinstallserver/__init__.py
rteinstallserver/rteinstallserver.py
rteInstallServer-0.0.1.dist-info/LICENSE
rteInstallServer-0.0.1.dist-info/METADATA
rteInstallServer-0.0.1.dist-info/WHEEL
rteInstallServer-0.0.1.dist-info/top_level.txt
rteInstallServer-0.0.1.dist-info/RECORD
