Metadata-Version: 2.1
Name: rteInstallServer
Version: 0.0.1
Summary: RTE server installation
Author: Hendrik du Toit
Author-email: hendrik@brightedge.co.za
License: UNKNOWN
Platform: UNKNOWN
Classifier: Development Status :: 1 - Planning
Classifier: Intended Audience :: Developers
Classifier: Topic :: Software Development
Classifier: License :: OSI Approved :: MIT License
Classifier: Programming Language :: Python :: 3.8
License-File: LICENSE
Requires-Dist: reahl-component (<6.1,>=6.0)
Requires-Dist: reahl-web (<6.1,>=6.0)
Requires-Dist: reahl-sqlalchemysupport (<6.1,>=6.0)
Requires-Dist: reahl-sqlitesupport (<6.1,>=6.0)
Requires-Dist: reahl-web-declarative (<6.1,>=6.0)
